synthax/__init__.py
synthax/config.py
synthax/functional.py
synthax/io.py
synthax/parameter.py
synthax/synth.py
synthax/types.py
synthax/modules/__init__.py
synthax/modules/amplifiers.py
synthax/modules/base.py
synthax/modules/blend.py
synthax/modules/control.py
synthax/modules/envelopes.py
synthax/modules/filters.py
synthax/modules/keyboard.py
synthax/modules/lfos.py
synthax/modules/mixers.py
synthax/modules/oscillators.py
synthax-0.2.2.dist-info/LICENSE
synthax-0.2.2.dist-info/METADATA
synthax-0.2.2.dist-info/WHEEL
synthax-0.2.2.dist-info/top_level.txt
synthax-0.2.2.dist-info/RECORD
