Metadata-Version: 2.1
Name: synthax
Version: 0.2.2
Summary: SynthAX: A Fast Modular Synthesizer in JAX
Home-page: https://github.com/PapayaResearch/synthax
Author: Manuel Cherep, Nikhil Singh
Author-email: mcherep@mit.edu, nsingh1@mit.edu
Classifier: Programming Language :: Python :: 3.9
Classifier: Programming Language :: Python :: 3.10
Classifier: Programming Language :: Python :: 3.11
Classifier: Programming Language :: Python :: 3.12
Classifier: License :: OSI Approved :: MIT License
Classifier: Operating System :: OS Independent
Requires-Python: >=3.9
License-File: LICENSE
Requires-Dist: jax >=0.3.0
Requires-Dist: jaxlib >=0.3.0
Requires-Dist: chex
Requires-Dist: flax
Requires-Dist: PyYAML
